fruityloops_mcp/__init__.py
fruityloops_mcp/__main__.py
fruityloops_mcp/midi_interface.py
fruityloops_mcp/server.py
fruityloops_mcp-1.0.0.dist-info/METADATA
fruityloops_mcp-1.0.0.dist-info/WHEEL
fruityloops_mcp-1.0.0.dist-info/entry_points.txt
fruityloops_mcp-1.0.0.dist-info/licenses/LICENSE
fruityloops_mcp-1.0.0.dist-info/RECORD
