Metadata-Version: 2.4
Name: fruityloops-mcp
Version: 1.0.0
Summary: MCP server for FL Studio (Fruity Loops) Python API integration
License-File: LICENSE
Requires-Python: >=3.10
Requires-Dist: fl-studio-api-stubs>=2.0.0
Requires-Dist: mcp>=1.0.0
Requires-Dist: mido>=1.3.0
Requires-Dist: python-rtmidi>=1.5.0
Provides-Extra: dev
Requires-Dist: pytest-asyncio>=0.23.0; extra == 'dev'
Requires-Dist: pytest-cov>=4.1.0; extra == 'dev'
Requires-Dist: pytest>=8.0.0; extra == 'dev'
Requires-Dist: ruff>=0.8.0; extra == 'dev'
Provides-Extra: docs
Requires-Dist: mkdocs-git-revision-date-localized-plugin>=1.2.0; extra == 'docs'
Requires-Dist: mkdocs-material>=9.5.0; extra == 'docs'
Requires-Dist: mkdocs>=1.5.0; extra == 'docs'
Requires-Dist: mkdocstrings[python]>=0.24.0; extra == 'docs'
